[
{
  "model": "ambassadors.ambassador",
  "pk": "052fbdfa-6a76-47a7-ae3d-faffa9a46de8",
  "fields": {
    "created": "2024-02-25",
    "updated": "2024-02-25",
    "telegram": "python_novice",
    "name": "Григорьев Павел Анатольевич",
    "status": "active",
    "onboarding_status": true,
    "sex": "m",
    "country": "Беларусь",
    "city": "Гродно",
    "address": "ул. Тестовая, д. 78, кв. 23",
    "index": "230011",
    "email": "pavel.grigoriev@example.com",
    "phone": "+375 33 765 43 21",
    "current_work": "Software Solutions Ltd.",
    "education": "Высшее программирование",
    "blog_link": "pavel-coder-blog.net",
    "clothing_size": "xl",
    "foot_size": "44",
    "comment": "Тестовый профиль с реалистичными данными, подходящими для тестирования веб-приложений и систем.",
    "education_goal": 1,
    "course": 18,
    "ambassador_goals": [
      4,
      7
    ]
  }
},
{
  "model": "ambassadors.ambassador",
  "pk": "2a6dfea2-c51d-4417-8249-9b4f5ebd71d5",
  "fields": {
    "created": "2024-02-25",
    "updated": "2024-02-25",
    "telegram": "dev_tester",
    "name": "Михайлов Артем Викторович",
    "status": "active",
    "onboarding_status": true,
    "sex": "m",
    "country": "Украина",
    "city": "Харьков",
    "address": "ул. Тестовая, д. 45, кв. 678",
    "index": "610123",
    "email": "artem.mikhaylov@example.com",
    "phone": "+380 66 123 45 67",
    "current_work": "IT Solutions Ltd.",
    "education": "Высшее компьютерные науки",
    "blog_link": "artem-dev-blog.org",
    "clothing_size": "xl",
    "foot_size": "41",
    "comment": "Тестовый профиль с реалистичными данными для эффективного тестирования системы.",
    "education_goal": 1,
    "course": 20,
    "ambassador_goals": [
      1,
      2,
      3
    ]
  }
},
{
  "model": "ambassadors.ambassador",
  "pk": "680e42a2-a4d2-4d8e-900b-539c36a5a303",
  "fields": {
    "created": "2024-02-25",
    "updated": "2024-02-25",
    "telegram": "coding_explorer",
    "name": "Кузнецов Игорь Дмитриевич",
    "status": "active",
    "onboarding_status": true,
    "sex": "Unknown",
    "country": "Украина",
    "city": "Львов",
    "address": "ул. Программистов, д. 67, кв. 890",
    "index": "790123",
    "email": "igor.kuznetsov@example.com",
    "phone": "+380 68 901 23 45",
    "current_work": "CodeCrafters LLC",
    "education": "Высшее информатика",
    "blog_link": "igor-code-adventures.org",
    "clothing_size": "xl",
    "foot_size": "42",
    "comment": "Тестовый профиль с реалистичными данными, идеально подходящий для тестирования функционала связанного с программированием.",
    "education_goal": 1,
    "course": 12,
    "ambassador_goals": [
      1,
      3,
      6
    ]
  }
},
{
  "model": "ambassadors.ambassador",
  "pk": "77a214c7-8d33-45b6-bb93-35cc65e8c02b",
  "fields": {
    "created": "2024-02-25",
    "updated": "2024-02-25",
    "telegram": "code_navigator",
    "name": "Смирнова Елена Александровна",
    "status": "not_ambassador",
    "onboarding_status": true,
    "sex": "w",
    "country": "Россия",
    "city": "Санкт-Петербург",
    "address": "пр. Примерный, д. 789, кв. 123",
    "index": "543210",
    "email": "elena.smirnova@example.com",
    "phone": "+7 921 345 67 89",
    "current_work": "ООО \"Кодовый Лаборатория\"",
    "education": "Высшее информационные технологии",
    "blog_link": "elena-coder.com",
    "clothing_size": "xs",
    "foot_size": "39",
    "comment": "Тестовый профиль для проверки функционала, предоставляющий реалистичные данные о пользователе.",
    "education_goal": 1,
    "course": 25,
    "ambassador_goals": [
      1,
      2,
      6
    ]
  }
},
{
  "model": "ambassadors.ambassador",
  "pk": "93f18548-2da7-4c17-b7eb-6d9be4be648a",
  "fields": {
    "created": "2024-02-25",
    "updated": "2024-02-25",
    "telegram": "user_tester23",
    "name": "Петрова Анна Сергеевна",
    "status": "paused",
    "onboarding_status": false,
    "sex": "w",
    "country": "Россия",
    "city": "Архангельск",
    "address": "бул. Тестовый, д. 567, кв. 890",
    "index": "567890",
    "email": "anna.petrova@example.com",
    "phone": "+380 67 890 12 34",
    "current_work": "ИТ-Консалтинг Групп",
    "education": "Среднее специальное",
    "blog_link": "annas-blog.net",
    "clothing_size": "s",
    "foot_size": "38",
    "comment": "Используется в тестировании как образец данных пользователя.",
    "education_goal": 2,
    "course": 10,
    "ambassador_goals": [
      1,
      6
    ]
  }
},
{
  "model": "ambassadors.ambassador",
  "pk": "e40ada25-7542-4327-9007-ef26266db60c",
  "fields": {
    "created": "2024-02-25",
    "updated": "2024-02-25",
    "telegram": "testing_guru",
    "name": "Жукова Ольга Владимировна",
    "status": "active",
    "onboarding_status": true,
    "sex": "w",
    "country": "Россия",
    "city": "Красноярск",
    "address": "пр. Тестовый, д. 89, кв. 567",
    "index": "660567",
    "email": "olga.zhukova@example.com",
    "phone": "+7 952 345 67 89",
    "current_work": "Quality Assurance Experts Ltd",
    "education": "Высшее тестирование программного обеспечения",
    "blog_link": "olga-testing-insights.com",
    "clothing_size": "xs",
    "foot_size": "39",
    "comment": "Тестовый профиль с разнообразными данными для эффективного тестирования различных аспектов системы.",
    "education_goal": 1,
    "course": 21,
    "ambassador_goals": [
      1,
      3
    ]
  }
},
{
  "model": "ambassadors.ambassador",
  "pk": "e958c1ca-64ec-46bc-b612-97364788a471",
  "fields": {
    "created": "2024-02-25",
    "updated": "2024-02-25",
    "telegram": "test_engineer",
    "name": "Соколова Мария Алексеевна",
    "status": "active",
    "onboarding_status": true,
    "sex": "w",
    "country": "Россия",
    "city": "Новосибирск",
    "address": "пер. Технический, д. 12, кв. 345",
    "index": "630123",
    "email": "maria.sokolova@example.com",
    "phone": "+7 913 876 54 32",
    "current_work": "QA Experts Group",
    "education": "Высшее тестирование программного обеспечени",
    "blog_link": "maria-tester-insights.com",
    "clothing_size": "xs",
    "foot_size": "38",
    "comment": "Тестовый профиль с разнообразными данными для проверки различных аспектов системы.",
    "education_goal": 2,
    "course": 7,
    "ambassador_goals": [
      1,
      3
    ]
  }
},
{
  "model": "ambassadors.ambassador",
  "pk": "e9e6c13f-f165-4ab5-bddb-2087179a8577",
  "fields": {
    "created": "2024-02-25",
    "updated": "2024-02-25",
    "telegram": "test_guru",
    "name": "Козлов Дмитрий Валерьевич",
    "status": "active",
    "onboarding_status": true,
    "sex": "m",
    "country": "Беларусь",
    "city": "Минск",
    "address": "пер. Тестовый, д. 34, кв. 567",
    "index": "220022",
    "email": "dmitry.kozlov@example.com",
    "phone": "+375 29 876 54 32",
    "current_work": "ООО \"Инновационные Решения\"",
    "education": "Высшее экономическое",
    "blog_link": "dmitry-blog.biz",
    "clothing_size": "m",
    "foot_size": "43",
    "comment": "Тестовый профиль с реалистичными данными для проверки функционала системы.",
    "education_goal": 1,
    "course": 9,
    "ambassador_goals": [
      1,
      2,
      3,
      4,
      5,
      6,
      7
    ]
  }
},
{
  "model": "ambassadors.ambassador",
  "pk": "eef48638-1356-41a4-9f2d-696a446eb1f3",
  "fields": {
    "created": "2024-02-25",
    "updated": "2024-02-25",
    "telegram": "tg_nickname_1",
    "name": "Александр Иванов",
    "status": "active",
    "onboarding_status": true,
    "sex": "m",
    "country": "Россия",
    "city": "Москва",
    "address": "ул. Ленина, д. 25, кв. 3",
    "index": "123456",
    "email": "alex@ya.ru",
    "phone": "+71234567891",
    "current_work": "ООО \"Тестовые Технологии\"",
    "education": "Высшее техническое",
    "blog_link": "ivanov-blog.com",
    "clothing_size": "m",
    "foot_size": "42",
    "comment": "Тестовый пользователь для проверки функционала.",
    "education_goal": 1,
    "course": 19,
    "ambassador_goals": [
      4,
      5
    ]
  }
},
{
  "model": "ambassadors.ambassador",
  "pk": "f60300e1-7484-4e06-8a4f-51963db6a949",
  "fields": {
    "created": "2024-02-25",
    "updated": "2024-02-25",
    "telegram": "test_coder",
    "name": "Лебедева Алина Игоревна",
    "status": "paused",
    "onboarding_status": false,
    "sex": "w",
    "country": "Россия",
    "city": "Екатеринбург",
    "address": "пр. Технологический, д. 56, кв. 789",
    "index": "620045",
    "email": "alina.lebedeva@example.com",
    "phone": "+7 922 567 89 01",
    "current_work": "Digital Innovations LLC",
    "education": "Высшее инженерно-техническое",
    "blog_link": "alina-coding-journey.com",
    "clothing_size": "xs",
    "foot_size": "37",
    "comment": "Тестовый профиль с реалистичными данными для проверки функционала системы с различными входными данными.",
    "education_goal": 2,
    "course": 4,
    "ambassador_goals": [
      4,
      6
    ]
  }
}
]
